visual_auditor/__init__.py
visual_auditor/adult.ipynb
visual_auditor/adult_common_samples.json
visual_auditor/adult_overlapping_samples.json
visual_auditor/adult_reverse_common_samples.json
visual_auditor/adult_reverse_overlapping_samples.json
visual_auditor/adult_reverse_slices.json
visual_auditor/adult_slices.json
visual_auditor/bundle.html
visual_auditor/common_samples.json
visual_auditor/cp_common_samples.json
visual_auditor/cp_overlapping_samples.json
visual_auditor/cp_reverse_common_samples.json
visual_auditor/cp_reverse_overlapping_samples.json
visual_auditor/cp_reverse_slices.json
visual_auditor/cp_slices.json
visual_auditor/customer_churn.ipynb
visual_auditor/gc_common_samples.json
visual_auditor/gc_overlapping_samples.json
visual_auditor/gc_reverse_common_samples.json
visual_auditor/gc_reverse_overlapping_samples.json
visual_auditor/gc_reverse_slices.json
visual_auditor/gc_slices.json
visual_auditor/german_credit.ipynb
visual_auditor/index.html
visual_auditor/overlapping_samples.json
visual_auditor/risk_control.py
visual_auditor/slice_finder.py
visual_auditor/slices.json
visual_auditor/visual_auditor.py
visual_auditor/.ipynb_checkpoints/adult-checkpoint.ipynb
visual_auditor/.ipynb_checkpoints/customer_churn-checkpoint.ipynb
visual_auditor/.ipynb_checkpoints/german_credit-checkpoint.ipynb
visual_auditor/data/adult.data
visual_auditor/data/adult.names
visual_auditor/data/adult.test
visual_auditor/data/customer_churn_prediction.csv
visual_auditor/data/german.csv
visual_auditor/data/german_credit_data.csv
visual_auditor/output/common_samples.json
visual_auditor/output/overlapping_samples.json
visual_auditor/output/slices.json
visual_auditor-0.1.3.dist-info/LICENSE
visual_auditor-0.1.3.dist-info/WHEEL
visual_auditor-0.1.3.dist-info/METADATA
visual_auditor-0.1.3.dist-info/RECORD
