Metadata-Version: 2.1
Name: visual_auditor
Version: 0.1.3
Summary: A Python package for visually auditing machine learning models for fairness through the use of interpretable visualizations summarizing intersectional bias.
Author-email: David Munechika <david.munechika@gatech.edu>
Classifier: License :: OSI Approved :: MIT License
Project-URL: Home, https://github.com/poloclub/visual-auditor
